odoo/addons/sale_order_secondary_unit/README.rst
odoo/addons/sale_order_secondary_unit/__init__.py
odoo/addons/sale_order_secondary_unit/__manifest__.py
odoo/addons/sale_order_secondary_unit/i18n/de.po
odoo/addons/sale_order_secondary_unit/i18n/es.po
odoo/addons/sale_order_secondary_unit/i18n/fi.po
odoo/addons/sale_order_secondary_unit/i18n/it.po
odoo/addons/sale_order_secondary_unit/i18n/sale_order_secondary_unit.pot
odoo/addons/sale_order_secondary_unit/i18n/zh_CN.po
odoo/addons/sale_order_secondary_unit/models/__init__.py
odoo/addons/sale_order_secondary_unit/models/product.py
odoo/addons/sale_order_secondary_unit/models/product_template.py
odoo/addons/sale_order_secondary_unit/models/sale_order.py
odoo/addons/sale_order_secondary_unit/readme/CONFIGURE.md
odoo/addons/sale_order_secondary_unit/readme/CONTRIBUTORS.md
odoo/addons/sale_order_secondary_unit/readme/DESCRIPTION.md
odoo/addons/sale_order_secondary_unit/readme/USAGE.md
odoo/addons/sale_order_secondary_unit/report/sale_report_templates.xml
odoo/addons/sale_order_secondary_unit/static/description/icon.png
odoo/addons/sale_order_secondary_unit/static/description/index.html
odoo/addons/sale_order_secondary_unit/tests/__init__.py
odoo/addons/sale_order_secondary_unit/tests/test_product_template.py
odoo/addons/sale_order_secondary_unit/tests/test_sale_order.py
odoo/addons/sale_order_secondary_unit/views/product_secondary_unit_views.xml
odoo/addons/sale_order_secondary_unit/views/product_views.xml
odoo/addons/sale_order_secondary_unit/views/sale_order_views.xml
odoo_addon_sale_order_secondary_unit-18.0.1.0.1.dist-info/METADATA
odoo_addon_sale_order_secondary_unit-18.0.1.0.1.dist-info/WHEEL
odoo_addon_sale_order_secondary_unit-18.0.1.0.1.dist-info/top_level.txt
odoo_addon_sale_order_secondary_unit-18.0.1.0.1.dist-info/RECORD
